{
  "addresses": [
    {
      "id": "id",
      "codice_archivio_or": "40",
      "progressivo_indirizzo_or": "100",
      "comune_or": "Roma",
      "localita_or": "",
      "indirizzo_originale": "Via di Monteverde 135",
      "localita_su": "",
      "dug_su": "via",
      "duf_su": "di Monteverde",
      "civico_su": "135",
      "esponente_su": "",
      "nota_su": "Indirizzo corretto",
      "validato": true,
      "revisionato": false,
      "dug": "10",
      "duf": "di Monteverde",
      "civico": "135",
      "esponente": "3",
      "localita": "Roma",
      "chiave_strada": "id",
      "chiave_civico": "3",
      "fonte": "Google maps"
    },
    {
      "id": "2",
      "codice_archivio_or": "40",
      "progressivo_indirizzo_or": "101",
      "comune_or": "Roma",
      "localita_or": "",
      "indirizzo_originale": "Via di Monteverde 140/A",
      "localita_su": "non lo so",
      "dug_su": "via di",
      "duf_su": "Monteverde",
      "civico_su": "140A",
      "esponente_su": "vv",
      "nota_su": "",
      "validato": true,
      "revisionato": true,
      "dug": "ARGINE",
      "duf": "di Monteverde",
      "civico": "140",
      "esponente": "b",
      "Localita": "",
      "chiave_strada": "3",
      "chiave_civico": "003",
      "fonte": "istat",
      "localita": "Roma"
    },
    {
      "id": "3",
      "codice_archivio_or": "40",
      "progressivo_indirizzo_or": "6869314",
      "comune_or": "Fondi",
      "localita_or": "",
      "indirizzo_originale": "VIA SPINETE I (3' TRATTO) 9/A",
      "localita_su": "",
      "dug_su": "VIA",
      "duf_su": "SPINETE I",
      "civico_su": "3",
      "esponente_su": "TRATTO 9 A",
      "nota_su": "",
      "validato": true,
      "revisionato": false,
      "dug": "via",
      "duf": "Spinete",
      "civico": "3",
      "esponente": "A",
      "localita": "Fondi",
      "chiave_strada": "12",
      "chiave_civico": "10",
      "fonte": "Istat"
    },
    {
      "id": "4",
      "codice_archivio_or": "40",
      "progressivo_indirizzo_or": "6859048",
      "comune_or": "Monte San Biagio",
      "localita_or": "",
      "indirizzo_originale": "VIA CARRO 1A TRAVERSA 10 A",
      "localita_su": "",
      "dug_su": "VIA",
      "duf_su": "CARRO",
      "civico_su": "id",
      "esponente_su": "A TRAVERSA 10 A",
      "nota_su": "",
      "validato": null,
      "revisionato": false,
      "dug": "VIA",
      "duf": "CARRO",
      "civico": "10",
      "esponente": "A",
      "Localita": "",
      "chiave_strada": "3",
      "chiave_civico": "5",
      "fonte": ""
    },
    {
      "id": "5",
      "codice_archivio_or": "40",
      "progressivo_indirizzo_or": "2406943",
      "comune_or": "Merano/Meran",
      "localita_or": "",
      "indirizzo_originale": "VIA XXIV MAGGIO-24.MAISTRASSE",
      "localita_su": "",
      "dug_su": "VIA",
      "duf_su": "IV NOVEMBRE",
      "civico_su": "4",
      "esponente_su": "N OVEMBERSTRASSE 42",
      "nota_su": "",
      "validato": null,
      "revisionato": false,
      "dug": "VIA",
      "duf": "IV NOVEMBRE",
      "civico": "42",
      "esponente": "3",
      "localita": "Merano",
      "chiave_strada": "MRN",
      "chiave_civico": "3",
      "fonte": "Istat"
    },
    {
      "id": "6",
      "codice_archivio_or": "40",
      "progressivo_indirizzo_or": "36735799",
      "comune_or": "Catania",
      "localita_or": "",
      "indirizzo_originale": "VIA BARTOLOMEO ALTAVILLA ISOL.A 14",
      "localita_su": "",
      "dug_su": "VIA",
      "duf_su": "BARTOLOMEO ALTAVILLA",
      "civico_su": "",
      "esponente_su": "IS OL A 14",
      "nota_su": "",
      "validato": null,
      "revisionato": false,
      "dug": "VIA",
      "duf": "BARTOLOMEO ALTAVILLA",
      "civico": "14",
      "esponente": "3",
      "localita": "Loc",
      "chiave_strada": "2",
      "chiave_civico": "14",
      "fonte": "Google maps"
    },
    {
      "id": "7",
      "codice_archivio_or": "40",
      "progressivo_indirizzo_or": "5478541",
      "comune_or": "Rignano sull'Arno",
      "localita_or": "",
      "indirizzo_originale": "VIA GEN. CARLO ALBERTO DALLA CHIESA 4",
      "localita_su": "",
      "dug_su": "",
      "duf_su": "",
      "civico_su": "",
      "esponente_su": "",
      "nota_su": "",
      "validato": null,
      "revisionato": false,
      "dug": "VIA",
      "duf": "CARLO ALBERTO DALLA CHIESA",
      "civico": "9",
      "esponente": "4",
      "localita": "Loc",
      "chiave_strada": "4",
      "chiave_civico": "4",
      "fonte": "Istat"
    },
    {
      "id": "8",
      "codice_archivio_or": "40",
      "progressivo_indirizzo_or": "12923246",
      "comune_or": "Tortona",
      "localita_or": "",
      "indirizzo_originale": "STR STR.PROV.POZZOLO F.RO 22 C",
      "localita_su": "",
      "dug_su": "",
      "duf_su": "Strada Vicinale del Pozzo 22",
      "civico_su": "",
      "esponente_su": "",
      "nota_su": "Strada corretta",
      "validato": null,
      "revisionato": false,
      "dug": "Strada Vicinale",
      "duf": "del Pozzo",
      "civico": "22",
      "esponente": "id",
      "localita": "Tortona",
      "chiave_strada": "2",
      "chiave_civico": "4",
      "fonte": "Street Map"
    },
    {
      "id": "9",
      "codice_archivio_or": "40",
      "progressivo_indirizzo_or": "572246",
      "comune_or": "MONTIGLIO MONFERRATO",
      "localita_or": "",
      "indirizzo_originale": "VIA ASTI 43",
      "localita_su": "sdfds",
      "dug_su": "VIA",
      "duf_su": "ASTI",
      "civico_su": "43",
      "esponente_su": "sdfdfsfds",
      "nota_su": "Credo che si possa migliorare la qualita",
      "validato": null,
      "revisionato": false,
      "dug": "Via",
      "duf": "viale",
      "civico": "12",
      "esponente": "del Piscaro",
      "localita": "Frascati",
      "chiave_strada": "3",
      "chiave_civico": "A",
      "fonte": "Google maps"
    },
    {
      "id": "10",
      "codice_archivio_or": "40",
      "progressivo_indirizzo_or": "163",
      "comune_or": "Cavallino",
      "localita_or": "",
      "indirizzo_originale": "VIA  ALESSANDRO MANZONI 37 A",
      "localita_su": "",
      "dug_su": "VIA",
      "duf_su": "ALESSANDRO MANZONI",
      "civico_su": "37",
      "esponente_su": "A",
      "nota_su": "",
      "validato": false,
      "revisionato": false,
      "dug": "",
      "duf": "",
      "civico": "",
      "esponente": "",
      "localita": "",
      "chiave_strada": "",
      "chiave_civico": "",
      "fonte": ""
    },
    {
      "id": "11",
      "codice_archivio_or": "40",
      "progressivo_indirizzo_or": "24414805",
      "comune_or": "Messina",
      "localita_or": "ARIELLA",
      "indirizzo_originale": "VIA ARIELLA 10",
      "localita_su": "ARIELLA",
      "dug_su": "VIA",
      "duf_su": "ARIELLA",
      "civico_su": "10",
      "esponente_su": "",
      "nota_su": "Proviamo se funziona",
      "validato": false,
      "revisionato": false,
      "dug": "via",
      "duf": "Ariella",
      "civico": "10",
      "esponente": "id",
      "localita": "Messina",
      "chiave_strada": "id",
      "chiave_civico": "id",
      "fonte": "Istat"
    }
  ],
  "dugs": [
    {
      "id": "1",
      "value": "ARCO"
    },
    {
      "id": "2",
      "value": "ARGINE"
    },
    {
      "id": "3",
      "value": "AUTOSTRADA"
    },
    {
      "id": "4",
      "value": "BAGLIO"
    },
    {
      "id": "5",
      "value": "BALUARDO"
    },
    {
      "id": "6",
      "value": "BANCHINA"
    },
    {
      "id": "7",
      "value": "BASTIONI"
    },
    {
      "id": "8",
      "value": "BIVIO"
    },
    {
      "id": "9",
      "value": "BORGATA"
    },
    {
      "id": "10",
      "value": "BORGHETTO"
    },
    {
      "id": "11",
      "value": "BORGO"
    },
    {
      "id": "12",
      "value": "CA'"
    },
    {
      "id": "13",
      "value": "CALATA"
    },
    {
      "id": "14",
      "value": "CALLE"
    },
    {
      "id": "15",
      "value": "CAMPAZZO"
    },
    {
      "id": "16",
      "value": "CAMPIELLO"
    },
    {
      "id": "17",
      "value": "CAMPO"
    },
    {
      "id": "18",
      "value": "CANTONE"
    },
    {
      "id": "19",
      "value": "CARRARA"
    },
    {
      "id": "20",
      "value": "CASA"
    },
    {
      "id": "21",
      "value": "CASALE"
    },
    {
      "id": "22",
      "value": "CASALI"
    },
    {
      "id": "23",
      "value": "CASCINA"
    },
    {
      "id": "24",
      "value": "CASCINE"
    },
    {
      "id": "25",
      "value": "CASE"
    },
    {
      "id": "26",
      "value": "CASE SPARSE"
    },
    {
      "id": "27",
      "value": "CENTRO"
    },
    {
      "id": "28",
      "value": "CENTRO ABITATO"
    },
    {
      "id": "29",
      "value": "CHIASSO"
    },
    {
      "id": "30",
      "value": "CIRCONVALLAZIONE"
    },
    {
      "id": "31",
      "value": "CIRCUMVALLAZIONE"
    },
    {
      "id": "32",
      "value": "CLAUSTRO"
    },
    {
      "id": "33",
      "value": "COL"
    },
    {
      "id": "34",
      "value": "COLLE"
    },
    {
      "id": "35",
      "value": "CONDOMINIO"
    },
    {
      "id": "36",
      "value": "CONTRA'"
    },
    {
      "id": "37",
      "value": "CONTRADA"
    },
    {
      "id": "38",
      "value": "CORSO"
    },
    {
      "id": "39",
      "value": "CORT"
    },
    {
      "id": "40",
      "value": "CORTE"
    },
    {
      "id": "41",
      "value": "CORTICELLA"
    },
    {
      "id": "42",
      "value": "CORTILE"
    },
    {
      "id": "43",
      "value": "CUPA"
    },
    {
      "id": "44",
      "value": "DIRAMAZIONE"
    },
    {
      "id": "45",
      "value": "DISCESA"
    },
    {
      "id": "46",
      "value": "FATTORIA"
    },
    {
      "id": "47",
      "value": "FONDACO"
    },
    {
      "id": "48",
      "value": "FONDAMENTA"
    },
    {
      "id": "49",
      "value": "FONDO"
    },
    {
      "id": "50",
      "value": "FRAZIONE"
    },
    {
      "id": "51",
      "value": "GALLERIA"
    },
    {
      "id": "52",
      "value": "GIARDINI"
    },
    {
      "id": "53",
      "value": "GIARDINO"
    },
    {
      "id": "54",
      "value": "GRADINATA"
    },
    {
      "id": "55",
      "value": "GRADINI"
    },
    {
      "id": "56",
      "value": "GRADONI"
    },
    {
      "id": "57",
      "value": "HAMEAU"
    },
    {
      "id": "58",
      "value": "ISOLA"
    },
    {
      "id": "59",
      "value": "ISOLATO"
    },
    {
      "id": "60",
      "value": "LARGHETTO"
    },
    {
      "id": "61",
      "value": "LARGO"
    },
    {
      "id": "62",
      "value": "LOCALITA"
    },
    {
      "id": "63",
      "value": "LOCALITA'"
    },
    {
      "id": "64",
      "value": "LOCALITA PODERE"
    },
    {
      "id": "65",
      "value": "LUNGADIGE"
    },
    {
      "id": "66",
      "value": "LUNGARGINE"
    },
    {
      "id": "67",
      "value": "LUNGARNO"
    },
    {
      "id": "68",
      "value": "LUNGO"
    },
    {
      "id": "69",
      "value": "LUNGO ADDA"
    },
    {
      "id": "70",
      "value": "LUNGO BRENTA"
    },
    {
      "id": "71",
      "value": "LUNGO DORA"
    },
    {
      "id": "72",
      "value": "LUNGO ISARCO"
    },
    {
      "id": "73",
      "value": "LUNGO LAGO"
    },
    {
      "id": "74",
      "value": "LUNGO MALLERO"
    },
    {
      "id": "75",
      "value": "LUNGO PO"
    },
    {
      "id": "76",
      "value": "LUNGO STURA"
    },
    {
      "id": "77",
      "value": "LUNGO TALVERA"
    },
    {
      "id": "78",
      "value": "LUNGO TANARO"
    },
    {
      "id": "79",
      "value": "LUNGOBISAGNO"
    },
    {
      "id": "80",
      "value": "LUNGOLAGO"
    },
    {
      "id": "81",
      "value": "LUNGOLARIO"
    },
    {
      "id": "82",
      "value": "LUNGOMARE"
    },
    {
      "id": "83",
      "value": "LUNGOSABATO"
    },
    {
      "id": "84",
      "value": "LUNGOSTURA"
    },
    {
      "id": "85",
      "value": "LUNGOTANARO"
    },
    {
      "id": "86",
      "value": "LUNGOTEVERE"
    },
    {
      "id": "87",
      "value": "MASO"
    },
    {
      "id": "88",
      "value": "MASSERIA"
    },
    {
      "id": "89",
      "value": "MOLO"
    },
    {
      "id": "90",
      "value": "MURA"
    },
    {
      "id": "91",
      "value": "NUCLEO"
    },
    {
      "id": "92",
      "value": "PARCO"
    },
    {
      "id": "93",
      "value": "PASSAGGIO"
    },
    {
      "id": "94",
      "value": "PASSEGGIATA"
    },
    {
      "id": "95",
      "value": "PIAZ"
    },
    {
      "id": "96",
      "value": "PIAZZA"
    },
    {
      "id": "97",
      "value": "PIAZZALE"
    },
    {
      "id": "98",
      "value": "PIAZZETTA"
    },
    {
      "id": "99",
      "value": "PODERE"
    },
    {
      "id": "100",
      "value": "PORTICO"
    },
    {
      "id": "101",
      "value": "PROLUNGAMENTO"
    },
    {
      "id": "102",
      "value": "PROVINCIALE"
    },
    {
      "id": "103",
      "value": "QUARTIERE"
    },
    {
      "id": "104",
      "value": "RAMO"
    },
    {
      "id": "105",
      "value": "RAMPA"
    },
    {
      "id": "106",
      "value": "RAMPE"
    },
    {
      "id": "107",
      "value": "RECINTO"
    },
    {
      "id": "108",
      "value": "REGIONE"
    },
    {
      "id": "109",
      "value": "RIONE"
    },
    {
      "id": "110",
      "value": "RIVA"
    },
    {
      "id": "111",
      "value": "RIVIERA"
    },
    {
      "id": "112",
      "value": "RONCO"
    },
    {
      "id": "113",
      "value": "ROTONDA"
    },
    {
      "id": "114",
      "value": "RUA"
    },
    {
      "id": "115",
      "value": "RUE"
    },
    {
      "id": "116",
      "value": "SALITA"
    },
    {
      "id": "117",
      "value": "SALIZADA"
    },
    {
      "id": "118",
      "value": "SCALINATA"
    },
    {
      "id": "119",
      "value": "SENTIERO"
    },
    {
      "id": "120",
      "value": "SESTIERE"
    },
    {
      "id": "121",
      "value": "SOBBORGO"
    },
    {
      "id": "122",
      "value": "SOTTOPASSAGGIO"
    },
    {
      "id": "123",
      "value": "SOTTOPORTICO"
    },
    {
      "id": "124",
      "value": "SOTTOVIA"
    },
    {
      "id": "125",
      "value": "STRADA"
    },
    {
      "id": "126",
      "value": "STRADA COMUNALE"
    },
    {
      "id": "127",
      "value": "STRADA PRIVATA"
    },
    {
      "id": "128",
      "value": "STRADA PROVINCIALE"
    },
    {
      "id": "129",
      "value": "STRADA REGIONALE"
    },
    {
      "id": "130",
      "value": "STRADA STATALE"
    },
    {
      "id": "131",
      "value": "STRADA VICINALE"
    },
    {
      "id": "132",
      "value": "STRADELLA"
    },
    {
      "id": "133",
      "value": "STRADELLO"
    },
    {
      "id": "134",
      "value": "STRADONE"
    },
    {
      "id": "135",
      "value": "STREDA"
    },
    {
      "id": "136",
      "value": "SUBBORGO"
    },
    {
      "id": "137",
      "value": "SUPERSTRADA"
    },
    {
      "id": "138",
      "value": "SUPPORTICO"
    },
    {
      "id": "139",
      "value": "TANGENZIALE"
    },
    {
      "id": "140",
      "value": "TRAVERSA"
    },
    {
      "id": "141",
      "value": "TRONCO"
    },
    {
      "id": "142",
      "value": "VIA"
    },
    {
      "id": "143",
      "value": "VIADOTTO"
    },
    {
      "id": "144",
      "value": "VIAL"
    },
    {
      "id": "145",
      "value": "VIALE"
    },
    {
      "id": "146",
      "value": "VIALETTO"
    },
    {
      "id": "147",
      "value": "VICO"
    },
    {
      "id": "148",
      "value": "VICOLETTI"
    },
    {
      "id": "149",
      "value": "VICOLETTO"
    },
    {
      "id": "150",
      "value": "VICOLO"
    },
    {
      "id": "151",
      "value": "VICOLO CHIUSO"
    },
    {
      "id": "152",
      "value": "VICOLO CIECO"
    },
    {
      "id": "153",
      "value": "VICOLO LUNGO"
    },
    {
      "id": "154",
      "value": "VICOLO STRETTO"
    },
    {
      "id": "155",
      "value": "VIELLA"
    },
    {
      "id": "156",
      "value": "VILLAGGIO"
    },
    {
      "id": "157",
      "value": "VILLETTA"
    },
    {
      "id": "158",
      "value": "VIOTTOLO"
    },
    {
      "id": "159",
      "value": "VIUZZA"
    },
    {
      "id": "160",
      "value": "VIUZZO"
    },
    {
      "id": "161",
      "value": "VOCABOLO"
    },
    {
      "id": "162",
      "value": "ZONA"
    }
  ]
}